{"document_id":"011d429af19e4a65e6964d5751b43149","filename":"Cleaning day 251205 external drive listing.xlsx","relative_path":"LAB CLEANING/Cleaning day 251205/Cleaning day 251205 external drive listing.xlsx","section":"01_Overview","has_text":true,"chunk_count":2,"full_text":"R1: Name | Description | Size | Free space | Current owner | Location | Data | Type | Data to be uploaded to Allas or Databank? | Data backed up | Other comments\nR2: Farkkilab1 | Red WD Passport | 4Tb | | | Minions | | | | | data from 2018, TOPACIO data from 2023\nR3: Farkkilab10 | Blue Samsung | 2TB | | Ada | Minions | | | | | Cell cycle project data\nR4: Farkkilab11 | Blue Samsung | 2TB | | | | | | | | This belonged to Ashwini\nR5: Farkkilab12\nR6: Farkkilab13 | Blue Samsung | 2Tb | | Hanna | Queendom | | | | | HE images\nR7: Farkkilab14 | Blue Samsung | 2Tb | | Ada | Minions | | | | | Julia's backups(?)\nR8: Farkkilab15 | Black Seagate | 5Tb | | Maria | Minions | | | | | This belonged to Ashwini\nR9: Farkkilab16 | Blue Samsung | 2Tb | | Sara | Queendom\nR10: Farkkilab17\nR11: Farkkilab18 | Blue Samsung | 2Tb | | Ziqi | Queendom\nR12: Farkkilab19 | Blue Samsung | 2Tb | | Zhihan | Queendom\nR13: Farkkilab2 | LaCie | 1Tb | | Silja | Queendom\nR14: Farkkilab20 | Blue Samsung | 2Tb | | | | | | | | This belonged to Aditi\nR15: Farkkilab21 | Black Seagate | 5Tb | | Maria | Minions\nR16: Farkkilab22 | Black Samsung | 8Tb | | Ziqi | Queendom | | | | | SPACE data\nR17: Farkkilab23 | Black Samsung | 8Tb | | Ziqi | Queendom | | | | | SPACE data\nR18: Farkkilab24 | Black Samsung | 8Tb | | Saun | Minions\n\n| | Ziqi | Queendom | | | | | SPACE data\nR17: Farkkilab23 | Black Samsung | 8Tb | | Ziqi | Queendom | | | | | SPACE data\nR18: Farkkilab24 | Black Samsung | 8Tb | | Saun | Minions\nR19: Farkkilab25_ColdStorage1 | Black SEAGATE | 20TB | 4.9TB | | Minions | | | | | Ashwini iPDC project data\nR20: Farkkilab27 | Black Samsung | 5Tb | | Aleksandra/Iga | Queendom | | | | | EyeMT/TLS data\nR21: Farkkilab28_ColdStorage2 | Black SEAGATE | 20TB | Unknown - \nMalfunctions when connected?? | | Minions | | | | | TLS project data\nR22: Farkkilab29_ColdStorage3 | Black SEAGATE | 20Tb | Unknown - \nMalfunctions when connected?? | Ada(?) | Minions | | | | | Cell cycle project(?)\nR23: Farkkilab3 | Black WD My Book | 8TB | | Ada | Minions | | | | | Old drive, used for data transfers\nR24: Farkkilab30_ColdStorage4 | Black SEAGATE | 20Tb | 0TB | Ziqi/Aleksandra | Queendom | | | | | SPACE, EyeMT, tCycIF\nR25: Farkkilab31_ColdStorage5 | Black SEAGATE | 20Tb | 12.5TB | Ada | Minions | | | | | ???\nR26: Farkkilab32 | Gray Seagate | 2Tb | | Ullis\nR27: Farkkilab4 | Black WD My Book | 8TB | | | Minions\nR28: Farkkilab5 | Black Seagate | 2Tb | | | Minions | | | | | Ashwini flow data\nR29: Farkkilab6\nR30: Farkkilab7\nR31: Farkkilab8 | Black Samsung | 1Tb | 1Tb | Saun(?) | Minions\nR32: Farkkilab9 | Black Seagate | 4Tb | | Ziqi | Queendom | | | | | Angela's old SSD - iCAN?\nR36: Yellow = Missing as of 28-05-25","metadata":{"source":{"filename":"Cleaning day 251205 external drive listing.xlsx","stem":"Cleaning day 251205 external drive listing","extension":".xlsx","relative_path":"LAB CLEANING/Cleaning day 251205/Cleaning day 251205 external drive listing.xlsx","absolute_path":"/Users/debashishdeb/Downloads/OMEIA-database/Overview/LAB CLEANING/Cleaning day 251205/Cleaning day 251205 external drive listing.xlsx","size_bytes":65668,"size_human":"64.13 KB","modified":"2026-05-27T02:23:52","mime_type":"application/vnd.openxmlformats-officedocument.spreadsheetml.sheet","hashes":{"md5":"6140c1485cdac65e0d04ea508b111978"}},"classification":{"family":"spreadsheet","extension":".xlsx","mime_type":"application/vnd.openxmlformats-officedocument.spreadsheetml.sheet","extractor":"openpyxl","status":"ok"},"extraction_metadata":{"sheet_names":["Sheet1"],"sheet_count":1},"converted_at":"2026-06-05T15:27:36"}}