{"document_id":"5dbe7d57a91476546cae8a10e41a8153","filename":"FARF_abstract_2024.docx","relative_path":"3_FA/5. Writing & dissemination/Conference material/FCF 2024 (North Carolina)/Abstract/FARF_abstract_2024.docx","section":"25_3_fa-20260602t171547z-3-001","has_text":true,"chunk_count":9,"full_text":"Title: Spatial analysis of Fanconi anemia tumors show hypofunctional immune infiltration and DNA damage\n\nPablo Siliceo-Portugal1,2, Ada Junquera-Mencia3, Luis A. Flores-Mejía1,2, Mahiru Trejo-León1, Fernando Pérez-Villatoro3, Anna Laury3, Renee Fisher4, Michael Epperly4, Aliesha González-Arenas1, Sara Frías1,5, Leonard Harris6,7,8, Joel Greenberger4, Eunike Velleuer9, Anniina Färkkilä3,10,11, Alfredo Rodríguez1,2\n\n1) Departamento de Medicina Genómica y Toxicología Ambiental, Instituto de Investigaciones, Biomédicas, Universidad Nacional Autónoma de México, México. 2) Laboratorio de Falla Medular y Carcinogénesis, Instituto Nacional de Pediatría, México. 3) Research Program in Systems Oncology, University of Helsinki, Helsinki, Finland. 4) University of Pittsburgh Medical Center, Pittsburgh, Pennsylvania, United States of America. 5) Laboratorio de Citogenética, Instituto Nacional de Pediatría, México. 6) Department of Biomedical Engineering, University of Arkansas, Fayetteville, Arkansas, United States. 7) Interdisciplinary Graduate Program in Cell and Molecular Biology, University of Arkansas, Fayetteville, Arkansas, United States. 8) Cancer Biology Program, Winthrop P Rockefeller Cancer Institute, University of Arkansas for Medical Sciences, Little Rock, Arkansas, United States. 9) Centre for Child and Adolescent Health, HELIOS Klinikum, 47805 Krefeld, Germany. 10) Department of Obstetrics and Gynecology, Helsinki University Hospital, Helsinki, Finland. 11) iCAN Digital Precision Cancer Medicine Flagship, Helsinki, Finland.\n\nIntroduction: Fanconi Anemia (FA) is a genetic syndrome caused by an impaired FA/BRCA DNA repair pathway. Clinical manifestations of the disease include bone marrow failure and an exacerbated predisposition to develop squamous cell carcinomas (SCC) at an early age. Their underlying DNA repair deficiency makes patients with FA hypersensitive to most conventional DNA-damage-based cancer treatments, stressing the need for alternative therapeutic approaches. The implementation of single-cell spatial technologies in the study of the tumor microenvironment (TME) have shown promising insights towards the development of new biomarkers targeting the reactivation of hypofunctional immune responses.\n\nObjective: Identify the underlying functional dynamics driving immune evasion and tumor development in FA SCC by mapping the spatial landscape of the TME using single-cell spatial proteomics.\n\nMaterials and methods: We performed multiplexed single-cell spatial analysis using whole-slide tissue cyclic immunofluorescence (t-CycIF) of 33 tissue slides cut from formalin-fixed paraffin-embedded (FFPE) anogenital and head and neck SCC tumor samples from both non-FA and FA patients, as well as wild type and FA mice treated orally with the potent carcinogen 4NQO. Slides underwent multiple cycles of immunofluorescent staining (t-CyCIF) and scanning (Rarecyte Finder II) with a panel of >20 fluorochrome-tagged antibodies, as well as H&E staining on sequential slides for pathologist annotation of regions of interest (ROI). The resulting cyclic scans were aligned and registered (ASHLAR) into a multidimensional image that was analyzed using state-of-the-art computational methods (SCIMAP, Napari, StarDist, MCMICRO) in the context of their tumor region, carcinogenic progression, tumor-immune architecture, and functional interactions.\n\nResults. We identified phenotypical heterogeneity among the annotated tumor regions, showing increased diversity of cellular neighborhoods that correlated with carcinogenic progression (Figure 1A). In human FA SCCs, there was an increase in cellular neighborhoods with DNA damage and an enrichment of tumor-associated macrophages and exhausted T cells along carcinogenic progression (Figure 1B). In the 4NQO carcinogenesis mouse model, changes in the FA mouse epithelium appeared early (8 weeks), in comparison to wild type mice, including extensive fields of cells with DNA damage (H2AX) that expressed proliferation markers (Ki67), and infiltration of immune cells, which are in close contact with DNA damaged epithelial cells (Figure 1C).\n\nConclusion: We profiled the TME of both human and mouse FA SCCs through single-cell proteomics and identified unique cellular neighborhoods along carcinogenic progression, where hypofunctional immune infiltration correlated with DNA damage presence in tumor cells and colocalization with immunosuppressive cell types.\n\nTranslational and Clinical Applicability: Through this project we have found novel insights accounting for spatial interactions involved in cancer development and immune evasion in FA SCC. Our data has produced clear hypothesis that can further be explored and validated experimentally to develop new immunotherapeutic combinations focusing on patient stratification and improved treatment regimes.","metadata":{"source":{"filename":"FARF_abstract_2024.docx","stem":"FARF_abstract_2024","extension":".docx","relative_path":"3_FA/5. Writing & dissemination/Conference material/FCF 2024 (North Carolina)/Abstract/FARF_abstract_2024.docx","absolute_path":"/Users/debashishdeb/Downloads/OMEIA-database/projects/3_FA-20260602T171547Z-3-001/3_FA/5. Writing & dissemination/Conference material/FCF 2024 (North Carolina)/Abstract/FARF_abstract_2024.docx","size_bytes":16676,"size_human":"16.29 KB","modified":"2024-05-14T14:38:38","mime_type":"application/vnd.openxmlformats-officedocument.wordprocessingml.document","hashes":{"md5":"8c9a4c8f5a0ffaf4d0e0e80a0d850c70"}},"classification":{"family":"word","extension":".docx","mime_type":"application/vnd.openxmlformats-officedocument.wordprocessingml.document","extractor":"python-docx","status":"ok"},"extraction_metadata":{"paragraph_count":9,"table_count":0,"core_properties":{"title":"","subject":"","author":"Marina Siliceo Portugal","keywords":"","created":"2024-05-14T17:38:00+00:00","modified":"2024-05-14T21:38:00+00:00","last_modified_by":"Marina Siliceo Portugal"}},"converted_at":"2026-06-05T15:28:45"}}