{"document_id":"a3d1982aa68d33f6f2f9e9a7db1000d8","filename":"ESSB_presentation_V3.1.pptx","relative_path":"5_Writing/Posters and presentations/ESSB_presentation_V3.1.pptx","section":"20_35_spacestat","has_text":true,"chunk_count":38,"full_text":"Ziqi Kang\n\nUniversity of Helsinki\nFärkkilä Lab\n\nSPACEstat: quantitative spatial point pattern and network analysis of the tumor microenvironment\n\nZiqi Kang\n\nUniversity of Helsinki\nFärkkilä Lab\n\nSPACEstat: quantitative spatial point pattern and network analysis of the tumor microenvironment\n\nBackground\n\nTumor microenvironment (TME) is a complex ecosystem. \nImproved methods to quantify the spatial TME are need to understand the tumor ecosystem.\n\n2\n\nQuantification of Physical TME\n\nSpeaker notes:\nTumor microenvironment is a complex ecosystem with clinical features, physical TME and functional TME. In order to better understand this complexity, we need to be able to quantify the spatial relationships and structures within the physical TME.\n\nBackground\n\nTumor microenvironment (TME) is a complex ecosystem. \nImproved methods to quantify the spatial TME are need to understand the tumor ecosystem.\n\n2\n\nQuantification of Physical TME\n\nSpeaker notes:\nTumor microenvironment is a complex ecosystem with clinical features, physical TME and functional TME. In order to better understand this complexity, we need to be able to quantify the spatial relationships and structures within the physical TME.\n\nBackground\n\nAims \nQuantifying spatial arrangement of single cells and their relationships to tissue compartments\n\n3\n\nSpeaker notes:\nWe developed SPACEstat aiming to: (1) quantify the spatial arrangement of single cells and their relationships to tissue compartments, and\n\nBackground\n\nAims \nQuantifying spatial arrangement of single cells and their relationships to tissue compartments\n\n3\n\nSpeaker notes:\nWe developed SPACEstat aiming to: (1) quantify the spatial arrangement of single cells and their relationships to tissue compartments, and\n\nBackground\n\nAims \nQuantifying spatial arrangement of single cells and their relationships to tissue compartments \nQuantifying cellular networks and their spatial relationships\n\n4\n\nSpeaker notes:\nquantify the cellular networks and their spatial relationships.\n\nBackground\n\nAims \nQuantifying spatial arrangement of single cells and their relationships to tissue compartments \nQuantifying cellular networks and their spatial relationships\n\n4\n\nSpeaker notes:\nquantify the cellular networks and their spatial relationships.\n\nOverview of SPACEstat workflow\n\nA toolkit allows quantitative assessment at single-cell level or per-slide, focusing on spatial metrics\n\n5\n\nSpeaker notes:\nWe describe the SPACEstat workflow in 3 steps. \n The input is data frame in csv or Anndata with minimum features of X, Y and cell type labels which can be derived from spatial proteomics or transcriptomics.\n\nOverview of SPACEstat workflow\n\nA toolkit allows quantitative assessment at single-cell level or per-slide, focusing on spatial metrics\n\n5\n\nSpeaker notes:\nWe describe the SPACEstat workflow in 3 steps. \n The input is data frame in csv or Anndata with minimum features of X, Y and cell type labels which can be derived from spatial proteomics or transcriptomics.\n\nOverview of SPACEstat workflow\n\nA toolkit allows quantitative assessment at single-cell level or per-slide, focusing on spatial metrics\n\n6\n\nSpeaker notes:\nSPACEStat has 2 main blocks in the step of spatial feature quantification, single-cell level\n\nOverview of SPACEstat workflow\n\nA toolkit allows quantitative assessment at single-cell level or per-slide, focusing on spatial metrics\n\n6\n\nSpeaker notes:\nSPACEStat has 2 main blocks in the step of spatial feature quantification, single-cell level\n\nOverview of SPACEstat workflow\n\nA toolkit allows quantitative assessment at single-cell level or per-slide, focusing on spatial metrics\n\n7\n\nSpeaker notes:\nAnd cellular network level\n\nOverview of SPACEstat workflow\n\nA toolkit allows quantitative assessment at single-cell level or per-slide, focusing on spatial metrics\n\n7\n\nSpeaker notes:\nAnd cellular network level\n\nOverview of SPACEstat workflow\n\nA toolkit allows quantitative assessment at single-cell level or per-slide, focusing on spatial metrics\n\n8\n\nSpeaker notes:\neach generate output features for both single-cell and sample level scientific questions.\n\nOverview of SPACEstat workflow\n\nA toolkit allows quantitative assessment at single-cell level or per-slide, focusing on spatial metrics\n\n8\n\nSpeaker notes:\neach generate output features for both single-cell and sample level scientific questions.\n\nOverview of SPACEstat workflow\n\nA toolkit allows quantitative assessment at single-cell level or per-slide, focusing on spatial metrics\n\n9\n\nSpeaker notes:\nFirst, I will introduce how SPACEstat can quantify the spatial distributions at the single-cell level.\n\nOverview of SPACEstat workflow\n\nA toolkit allows quantitative assessment at single-cell level or per-slide, focusing on spatial metrics\n\n9\n\nSpeaker notes:\nFirst, I will introduce how SPACEstat can quantify the spatial distributions at the single-cell level.\n\nCalculate the cell-cell nearest neighbour distance distribution, provide median distance and AUC\n\nCalculate the basic spatial features per cell type (e.g. Cluster density, Gini Density, etc)\n\n10\n\nSPACEstat quantifies spatial distribution at single-cell level\n\nSpeaker notes:\nTo understand the spatial TME; we first need to quantify the cellular distance distributions. \nThis step does not require extra input from users, SPACEstat can calculate the cell-cell nearest neighbour distance distribution and provide median distance\n\nCalculate the cell-cell nearest neighbour distance distribution, provide median distance and AUC\n\nCalculate the basic spatial features per cell type (e.g. Cluster density, Gini Density, etc)\n\n10\n\nSPACEstat quantifies spatial distribution at single-cell level\n\nSpeaker notes:\nTo understand the spatial TME; we first need to quantify the cellular distance distributions. \nThis step does not require extra input from users, SPACEstat can calculate the cell-cell nearest neighbour distance distribution and provide median distance\n\n11\n\nSPACEstat quantifies spatial distribution at single-cell level\n\nCalculate the cell-cell nearest neighbour distance distribution, provide median distance and AUC\n\nCalculate the basic spatial features per cell type (e.g. Cluster density, Gini Density, etc)\n\nSpeaker notes:\n… and shown in a heatmap. Importantly, with SPACEstat you can quantify the basic spatial features of each cell type to better understand the conditions of the slide before you process with more detailed analysis [motivations!]. \n\nSPACEstat can go through each cell type and calculate the features such as cluster density or Gini density, which can describe how the cells distributed in the tissue.\n\n11\n\nSPACEstat quantifies spatial distribution at single-cell level\n\nCalculate the cell-cell nearest neighbour distance distribution, provide median distance and AUC\n\nCalculate the basic spatial features per cell type (e.g. Cluster density, Gini Density, etc)\n\nSpeaker notes:\n… and shown in a heatmap. Importantly, with SPACEstat you can quantify the basic spatial features of each cell type to better understand the conditions of the slide before you process with more detailed analysis [motivations!]. \n\nSPACEstat can go through each cell type and calculate the features such as cluster density or Gini density, which can describe how the cells distributed in the tissue.\n\n12\n\nUser can define: \nCell types of interest, e.g. immune cells\nRegion compartments of interest, e.g. tumor & stroma\nThreshold for cell type ratios to determine the compartment labels\n\nSPACEstat quantifies spatial distribution at single-cell level\n\nSpeaker notes:\nNext, with SPACEstat you can quantify cellular compartment infiltration. \n\nUsers can define the cell types and the type of compartments they want to study, also the threshold for context determination.\n\n12\n\nUser can define: \nCell types of interest, e.g. immune cells\nRegion compartments of interest, e.g. tumor & stroma\nThreshold for cell type ratios to determine the compartment labels\n\nSPACEstat quantifies spatial distribution at single-cell level\n\nSpeaker notes:\nNext, with SPACEstat you can quantify cellular compartment infiltration. \n\nUsers can define the cell types and the type of compartments they want to study, also the threshold for context determination.\n\nimmune infiltration index (I3) =\nimmune_density_tumor / immune_density_stroma\n\n13\n\nSPACEstat quantifies spatial distribution at single-cell level\n\nUser can define: \nCell types of interest, e.g. immune cells\nRegion compartments of interest, e.g. tumor & stroma\nThreshold for cell type ratios to determine the compartment labels\n\nSpeaker notes:\nHere on the slide immune cells were used as an example. \n\nBased on the cellular compartment labels, the users can calculate the immune infiltration index by dividing the density of immune cells in 2 tissue compartments.\n\nimmune infiltration index (I3) =\nimmune_density_tumor / immune_density_stroma\n\n13\n\nSPACEstat quantifies spatial distribution at single-cell level\n\nUser can define: \nCell types of interest, e.g. immune cells\nRegion compartments of interest, e.g. tumor & stroma\nThreshold for cell type ratios to determine the compartment labels\n\nSpeaker notes:\nHere on the slide immune cells were used as an example. \n\nBased on the cellular compartment labels, the users can calculate the immune infiltration index by dividing the density of immune cells in 2 tissue compartments.\n\n14\n\nSPACEstat quantifies spatial distribution at single-cell level\n\nUser can identify the interface between any 2 groups of cells\nUser can define the cell type of interest and \nCalculate the distance between cell <—> interface (global or per-side).\n\nSpeaker notes:\nInteraction between compartments creates interfaces. \n\nTo enable quantification of the spatial relationships to the tissue interfaces, Users can specify the interface between 2 groups of the cells, depends on the research questions.\n\n14\n\nSPACEstat quantifies spatial distribution at single-cell level\n\nUser can identify the interface between any 2 groups of cells\nUser can define the cell type of interest and \nCalculate the distance between cell <—> interface (global or per-side).\n\nSpeaker notes:\nInteraction between compartments creates interfaces. \n\nTo enable quantification of the spatial relationships to the tissue interfaces, Users can specify the interface between 2 groups of the cells, depends on the research questions.\n\n15\n\nUser can identify the interface between any 2 groups of cells\nUser can define the cell type of interest and \nCalculate the distance between cell <—> interface (global or per-side).\n\nSPACEstat quantifies spatial distribution at single-cell level\n\nSpeaker notes:\nAfter interface identification, users can define a list of cell types of interest and calculated the distance from cell to the interface, globally (if you don’t do the previous step) or per compartment. \n\nTo help you understand more about how we can use the results until current step,\n\n15\n\nUser can identify the interface between any 2 groups of cells\nUser can define the cell type of interest and \nCalculate the distance between cell <—> interface (global or per-side).\n\nSPACEstat quantifies spatial distribution at single-cell level\n\nSpeaker notes:\nAfter interface identification, users can define a list of cell types of interest and calculated the distance from cell to the interface, globally (if you don’t do the previous step) or per compartment. \n\nTo help you understand more about how we can use the results until current step,\n\nFindings - 1 with SPACEstat: immune aggregation on TSI in ovarian tumor ATRi therapy responder & non-responder\n\n16\n\nPD1+ CD8 T cells were significantly closer to the stromal side of the TSI in the responders compared to the non-responders\n\nDataset: \n12 whole slide Immunofluorescence images; \n6 Responders vs 6 non-responders.\n\nUnpublished result, please do not post\n\nSpeaker notes:\nI’m showing here a biological discovery that can be made based on the spatial quantification on single-cell level. \nWe used a dataset of 12 whole slide images from ovarian cancer. \n\nWe found the T cells and PD1+ CD8 T cells were located significantly closer to the stromal side of the TSI in the tumors that responded to ATRi -a targeted therapeutic-, in comparison to the non-responders.\n\nFindings - 1 with SPACEstat: immune aggregation on TSI in ovarian tumor ATRi therapy responder & non-responder\n\n16\n\nPD1+ CD8 T cells were significantly closer to the stromal side of the TSI in the responders compared to the non-responders\n\nDataset: \n12 whole slide Immunofluorescence images; \n6 Responders vs 6 non-responders.\n\nUnpublished result, please do not post\n\nSpeaker notes:\nI’m showing here a biological discovery that can be made based on the spatial quantification on single-cell level. \nWe used a dataset of 12 whole slide images from ovarian cancer. \n\nWe found the T cells and PD1+ CD8 T cells were located significantly closer to the stromal side of the TSI in the tumors that responded to ATRi -a targeted therapeutic-, in comparison to the non-responders.\n\nOverview of SPACEstat workflow\n\nA toolkit allows quantitative assessment at single-cell level or per-slide, focusing on spatial metrics\n\n17\n\nSpeaker notes:\nBack to the method part, and I will introduce the second block “Quantify cellular network structures”.\n\nOverview of SPACEstat workflow\n\nA toolkit allows quantitative assessment at single-cell level or per-slide, focusing on spatial metrics\n\n17\n\nSpeaker notes:\nBack to the method part, and I will introduce the second block “Quantify cellular network structures”.\n\n18\n\nSPACEstat enables cellular network and spatial pattern analysis\n\nUser can choose 1 or multiple cell types to generate the network\nRecord the feature of the networks.\n\nSet threshold of longest edge\n\nSpeaker notes:\nTo uncover how cells forming networks across slide.\n\nUser can choose the cell types to generate the network and\n\n18\n\nSPACEstat enables cellular network and spatial pattern analysis\n\nUser can choose 1 or multiple cell types to generate the network\nRecord the feature of the networks.\n\nSet threshold of longest edge\n\nSpeaker notes:\nTo uncover how cells forming networks across slide.\n\nUser can choose the cell types to generate the network and\n\n19\n\nSPACEstat enables cellular network and spatial pattern analysis\n\nUser can choose 1 or multiple cell types to generate the network\nRecord the feature of the networks.\n\nSet threshold of longest edge\n\nSpeaker notes:\n… record the features of the networks such as the total number of components and the size largest components. \n\nIn the package, there will also be a data object to store the network components with the X, Y coordinates. \n\nThe only parameter to tune is the longest edge allowed when forming the network, we will provide functions for user to diagnose and choose a proper threshold.\n\n19\n\nSPACEstat enables cellular network and spatial pattern analysis\n\nUser can choose 1 or multiple cell types to generate the network\nRecord the feature of the networks.\n\nSet threshold of longest edge\n\nSpeaker notes:\n… record the features of the networks such as the total number of components and the size largest components. \n\nIn the package, there will also be a data object to store the network components with the X, Y coordinates. \n\nThe only parameter to tune is the longest edge allowed when forming the network, we will provide functions for user to diagnose and choose a proper threshold.\n\n20\n\nTumor ecosystem is not just a collection of independent cells; it’s a dynamic, interconnected network of interactions\n\nSPACEstat enables cellular network and spatial pattern analysis\n\nSpeaker notes:\nWe know the tumor ecosystem is not just a collection of independent cells, and especially the immune cells form spatially interconnected networks. \n\nA natural intuitive is that if 2 cellular networks\n\n20\n\nTumor ecosystem is not just a collection of independent cells; it’s a dynamic, interconnected network of interactions\n\nSPACEstat enables cellular network and spatial pattern analysis\n\nSpeaker notes:\nWe know the tumor ecosystem is not just a collection of independent cells, and especially the immune cells form spatially interconnected networks. \n\nA natural intuitive is that if 2 cellular networks\n\nCD4 network\nCD8 network\n\n21\n\nTumor ecosystem is not just a collection of independent cells; it’s a dynamic, interconnected network of interactions\n\nSPACEstat enables cellular network and spatial pattern analysis\n\n21\n\nSpeaker notes:\nlike this example of CD4T cells and CD8T cells. They are highly mixed with each other at this point, we can thus\n\nCD4 network\nCD8 network\n\n21\n\nTumor ecosystem is not just a collection of independent cells; it’s a dynamic, interconnected network of interactions\n\nSPACEstat enables cellular network and spatial pattern analysis\n\n21\n\nSpeaker notes:\nlike this example of CD4T cells and CD8T cells. They are highly mixed with each other at this point, we can thus\n\n22\n\nCD4 network\nCD8 network\n\nTumor ecosystem is not just a collection of independent cells; it’s a dynamic, interconnected network of interactions\n\nSPACEstat enables cellular network and spatial pattern analysis\n\nSpeaker notes:\nmark this place using a polygon\n\n22\n\nCD4 network\nCD8 network\n\nTumor ecosystem is not just a collection of independent cells; it’s a dynamic, interconnected network of interactions\n\nSPACEstat enables cellular network and spatial pattern analysis\n\nSpeaker notes:\nmark this place using a polygon\n\n<— This is one “hub”!\n\n23\n\nCD4 network\nCD8 network\n\nTumor ecosystem is not just a collection of independent cells; it’s a dynamic, interconnected network of interactions\n\nSPACEstat enables cellular network and spatial pattern analysis\n\n23\n\nSpeaker notes:\nand call it as a network hub! \n\nSPACEstat can record the polygons, the cells inside them and their centroid locations. Which can be used in the downstream analysis\n\n<— This is one “hub”!\n\n23\n\nCD4 network\nCD8 network\n\nTumor ecosystem is not just a collection of independent cells; it’s a dynamic, interconnected network of interactions\n\nSPACEstat enables cellular network and spatial pattern analysis\n\n23\n\nSpeaker notes:\nand call it as a network hub! \n\nSPACEstat can record the polygons, the cells inside them and their centroid locations. Which can be used in the downstream analysis\n\nEvent: Interaction between 2 cellular networks (e.g. CD4T & CD8T)\nWe can study how does this event distribute across the space (clustering? Dispersed?)\n\n24\n\nSPACEstat enables cellular network and spatial pattern analysis\n\nSpeaker notes:\nConsider the interaction of 2 network components as an event. \n\nAcross the whole image you are studying, there are many such events happening. \nHow can you describe their behavior per slide? To quantify it, you need this step “spatial pattern analysis”.\n\nEvent: Interaction between 2 cellular networks (e.g. CD4T & CD8T)\nWe can study how does this event distribute across the space (clustering? Dispersed?)\n\n24\n\nSPACEstat enables cellular network and spatial pattern analysis\n\nSpeaker notes:\nConsider the interaction of 2 network components as an event. \n\nAcross the whole image you are studying, there are many such events happening. \nHow can you describe their behavior per slide? To quantify it, you need this step “spatial pattern analysis”.\n\n25\n\nEvent: Interaction between 2 cellular networks (e.g. CD4T & CD8T)\nWe can study how does this event distribute across the space (clustering? Dispersed?)\n\nSPACEstat enables cellular network and spatial pattern analysis\n\nSpeaker notes:\nThere is one example of Ripley’s K function used in ecology, to describe the distribution of objects in space. (description of the figure). \n\nIn SPACEstat we have included several functions for spatial analysis.\n\n25\n\nEvent: Interaction between 2 cellular networks (e.g. CD4T & CD8T)\nWe can study how does this event distribute across the space (clustering? Dispersed?)\n\nSPACEstat enables cellular network and spatial pattern analysis\n\nSpeaker notes:\nThere is one example of Ripley’s K function used in ecology, to describe the distribution of objects in space. (description of the figure). \n\nIn SPACEstat we have included several functions for spatial analysis.\n\nFindings - 2: Immune hub organisation can be used to stratify samples\n\n26\n\n79 whole slide Immunofluorescence images from ovarian cancer patients\n17 markers, 10 cell types\n2 subtypes (HRD & HRP)\n\nUnpublished result, please do not post\n\nPanCK\naSMA\nCD20\nCD8a\n\nHRP\n\nHRD\n\nSpeaker notes:\nTo be able to better understand a heterogenicity of cell interactions, we can cluster the immune hub spatial patterns across the dataset. \n\nWe used a dataset including 79 metastatic ovarian cancer whole slide images to quantify the network structures in the TME. \nWe build 2 networks for lymphonets and myelonets, and explore their spatial interactions.\n\nFindings - 2: Immune hub organisation can be used to stratify samples\n\n26\n\n79 whole slide Immunofluorescence images from ovarian cancer patients\n17 markers, 10 cell types\n2 subtypes (HRD & HRP)\n\nUnpublished result, please do not post\n\nPanCK\naSMA\nCD20\nCD8a\n\nHRP\n\nHRD\n\nSpeaker notes:\nTo be able to better understand a heterogenicity of cell interactions, we can cluster the immune hub spatial patterns across the dataset. \n\nWe used a dataset including 79 metastatic ovarian cancer whole slide images to quantify the network structures in the TME. \nWe build 2 networks for lymphonets and myelonets, and explore their spatial interactions.\n\nFindings - 2: Immune hub organisation can be used to stratify samples\n\n27\n\nUnpublished result, please do not post\n\nSpeaker notes:\nIn the heatmap, we identified 7 different clusters, each showing distinct spatial feature metrics. \n\nNotably, the samples differ in how strongly their immune hubs are spatially clustered across tissue scales. \n\nAn example from cluster 0 show strong cluster across all spatial scales from 0-5000 µm. That means immune hubs are clustered in short distance and those clusters also connect over longer distances across the tissue\n\nFindings - 2: Immune hub organisation can be used to stratify samples\n\n27\n\nUnpublished result, please do not post\n\nSpeaker notes:\nIn the heatmap, we identified 7 different clusters, each showing distinct spatial feature metrics. \n\nNotably, the samples differ in how strongly their immune hubs are spatially clustered across tissue scales. \n\nAn example from cluster 0 show strong cluster across all spatial scales from 0-5000 µm. That means immune hubs are clustered in short distance and those clusters also connect over longer distances across the tissue\n\nFindings - 2: Immune hub organisation can be used to stratify samples\n\n28\n\nUnpublished result, please do not post\n\nSpeaker notes:\n. In another example from cluster 5, the immune hubs show clustering in short distances but then distributed randomly in long distances, indicating a lack of large scale structures.\n\nFindings - 2: Immune hub organisation can be used to stratify samples\n\n28\n\nUnpublished result, please do not post\n\nSpeaker notes:\n. In another example from cluster 5, the immune hubs show clustering in short distances but then distributed randomly in long distances, indicating a lack of large scale structures.\n\nSPACEstat is a user-friendly package with a visualization solution\n\nVisualization - with Re-run\n\n29\n\nSpeaker notes:\nFor user friendly application we integrated SPACEstat with scanpy and implemented with Re-run, to ensure users can visualize the spatial structures and networks\n\nSPACEstat is a user-friendly package with a visualization solution\n\nVisualization - with Re-run\n\n29\n\nSpeaker notes:\nFor user friendly application we integrated SPACEstat with scanpy and implemented with Re-run, to ensure users can visualize the spatial structures and networks\n\nConclusions\n\nSPACEstat standardises spatial measurements within each slide, enabling comparison at the single-cell level, and across samples.\n\nSPACEstat uncovers functionally meaningful cell–cell and region-specific interactions. \n\nSPACEstat extends beyond cell–cell distances to quantify immune network topology and hub regularity.\n\nWant to know more?\nPlease come to our poster: 195 :)\n\nConclusions\n\nSPACEstat standardises spatial measurements within each slide, enabling comparison at the single-cell level, and across samples.\n\nSPACEstat uncovers functionally meaningful cell–cell and region-specific interactions. \n\nSPACEstat extends beyond cell–cell distances to quantify immune network topology and hub regularity.\n\nWant to know more?\nPlease come to our poster: 195 :)\n\nAcknowledgements\n\nAnniina Färkkilä\nAleksandra Shabanova \nElias Ruuska\nFernando Perez\nInga-Maria Launonen\nAda Junquera\nIga Niemiec\nMatilda Salko\nMaria Hincapie\nZhihan Liang\nPablo Siliceo Portugal\nWenqing Chen\nJoonas Jukonen\nSara Palomino\nAndreas Hainari\nSaundarya Shah\nAnastasia Lundgren\nElla Anttila\nAnni Härkönen\nAnni Suoknuuti\nAino Elomaa\nAlva Grönholm\nUlla-Maija Haltia\nLaura Haapasalo\nMaija Väärikoski\nSilja Kauppila\n\n\nCollaborators: \nMariike Kuijjer\n\n\nONCOSYS\nONCOSYS-OVA\n\nThanks for listening!\n\n<— Follow our lab website \n for upcoming pre-print!\n\nEmail me: ziqi.kang@helsinki.fi\n\nSpeaker notes:\nThanks\n\nFollow our lab website for upcoming pre-print! \nPlease email me\n\nAcknowledgements\n\nAnniina Färkkilä\nAleksandra Shabanova \nElias Ruuska\nFernando Perez\nInga-Maria Launonen\nAda Junquera\nIga Niemiec\nMatilda Salko\nMaria Hincapie\nZhihan Liang\nPablo Siliceo Portugal\nWenqing Chen\nJoonas Jukonen\nSara Palomino\nAndreas Hainari\nSaundarya Shah\nAnastasia Lundgren\nElla Anttila\nAnni Härkönen\nAnni Suoknuuti\nAino Elomaa\nAlva Grönholm\nUlla-Maija Haltia\nLaura Haapasalo\nMaija Väärikoski\nSilja Kauppila\n\n\nCollaborators: \nMariike Kuijjer\n\n\nONCOSYS\nONCOSYS-OVA\n\nThanks for listening!\n\n<— Follow our lab website \n for upcoming pre-print!\n\nEmail me: ziqi.kang@helsinki.fi\n\nSpeaker notes:\nThanks\n\nFollow our lab website for upcoming pre-print! \nPlease email me\n\nmax_l_obs\n\nr_maxL\n\nr_decayL\n\nslope_at_origin\n\nmax_pcf\n\nr_decayg\n\nr_maxg\n\nmean_pcf_short\n\nmean_pcf_mid\n\nmax_l_obs\n\nr_maxL\n\nr_decayL\n\nslope_at_origin\n\nmax_pcf\n\nr_decayg\n\nr_maxg\n\nmean_pcf_short\n\nmean_pcf_mid\n\nUnpublished result, please do not post\n\nUnpublished result, please do not post\n\nFindings - 2: High immune-TSI distance in a group of worse prognosis patients\n\nA\n\nB\n\nC\n\nD\n\nD\n\nE\n\nE\n\nF\n\n]\n\nF\n\nFindings - 2: High immune-TSI distance in a group of worse prognosis patients\n\nA\n\nB\n\nC\n\nD\n\nD\n\nE\n\nE\n\nF\n\n]\n\nF\n\nFindings - 3: Immune hub organisation is relevant with the progression-free survival of patients\n\nFindings - 3: Immune hub organisation is relevant with the progression-free survival of patients\n\nFindings - 3: Immune hub organisation is relevant with the progression-free survival of patients\n\n37\n\nFindings - 3: Immune hub organisation is relevant with the progression-free survival of patients\n\n37\n\nGeneralization & Visualization\n\nTo test whether SPACEstat generalizes beyond ovarian cancer, we will apply SPACEstat on 2 independent datasets from different platforms: MIBI-TOF in breast cancer and CODEX in colorectal cancer. \n\nVisualization - with Re-run\n\nGeneralization & Visualization\n\nTo test whether SPACEstat generalizes beyond ovarian cancer, we will apply SPACEstat on 2 independent datasets from different platforms: MIBI-TOF in breast cancer and CODEX in colorectal cancer. \n\nVisualization - with Re-run\n\nGeneralization & Visualization\n\nVisualization - with Re-run\n\nGeneralization & Visualization\n\nVisualization - with Re-run","metadata":{"source":{"filename":"ESSB_presentation_V3.1.pptx","stem":"ESSB_presentation_V3.1","extension":".pptx","relative_path":"5_Writing/Posters and presentations/ESSB_presentation_V3.1.pptx","absolute_path":"/Users/debashishdeb/Downloads/OMEIA-database/projects/35_SPACEstat/5_Writing/Posters and presentations/ESSB_presentation_V3.1.pptx","size_bytes":48473914,"size_human":"46.23 MB","modified":"2026-05-26T02:40:22","mime_type":"application/vnd.openxmlformats-officedocument.presentationml.presentation","hashes":{"md5":"5786632635671b7971b0409ae3067d94"}},"classification":{"family":"presentation","extension":".pptx","mime_type":"application/vnd.openxmlformats-officedocument.presentationml.presentation","extractor":"python-pptx","status":"ok"},"extraction_metadata":{"slide_count":39},"converted_at":"2026-06-05T15:28:30"}}