{"document_id":"b3ddc1e758d4dc6484c79503a751f5ca","filename":"CellposeSetup_Instructions.md","relative_path":"Data & Figures/Data/2. Proteopicks/Protocols/CellposeSetup_Instructions.md","section":"26_4_cellcycle","has_text":true,"chunk_count":1,"full_text":"**How to set up Cellpose** (for Windows)\n\n1. Open Anaconda prompt\n\n2. Create Environment:\n\nconda create -n cellpose_env python=3.8\\\n(Cellpose works with Python 3.8+)\n\n3. Activate Environment:\\\n conda activate cellpose_env\n\n4. Install packages :\n\npip install cellpose\\\n(should automatically include numpy, scipy, tiffile, pytorch, pyqtgraph,\nPyQt5 or alternatives like pyside or PyQt6, numba, natsort, fastremap,\nroifile, superqt)","metadata":{"source":{"filename":"CellposeSetup_Instructions.md","stem":"CellposeSetup_Instructions","extension":".md","relative_path":"Data & Figures/Data/2. Proteopicks/Protocols/CellposeSetup_Instructions.md","absolute_path":"/Users/debashishdeb/Downloads/OMEIA-database/projects/4_CellCycle/Data & Figures/Data/2. Proteopicks/Protocols/CellposeSetup_Instructions.md","size_bytes":438,"size_human":"438.00 B","modified":"2026-06-02T14:11:24","mime_type":"text/markdown","hashes":{"md5":"fbe898488a342669f7f6a9a1a75a8f38"}},"classification":{"family":"text","extension":".md","mime_type":"text/markdown","extractor":"text","status":"ok"},"extraction_metadata":{"encoding":"utf_8","line_count":18},"converted_at":"2026-06-05T15:28:44"}}