{"document_id":"0a41d5700cac07115526d7be4dd2c543","filename":"2024_12_19_EyeMT_9_with_TLS_7_GeoMxslides_Sectioning_Order .xlsx","relative_path":"Orders for slides and sections/2024_Sectioning orders/2024_12_19_EyeMT_9_with_TLS_7_GeoMxslides_Sectioning_Order .xlsx","section":"04_Wet_Lab","has_text":true,"chunk_count":2,"full_text":"R1: Pairs of blocks for sectioning | Up | Down | Number of slides\nR2: 1st pair | S309_ iOme | S225_iOme | 6 per pair\nR3: 2nd pair | S380_iOme | S106_iOme | 6 per pair\nR4: 3rd pair | S120_iOme | S378_iOme | 6 per pair\nR5: 4th pair | S311_iOme | S355_iOme | 6 per pair\nR6: 5th pair | S080_iOme2 | S088_iOme | 6 per pair\nR7: 6th pair | S195_iOme1 | S118_iOme | 6 per pair\nR8: 7th pair | S091_iOme1 | S112_iOme | 6 per pair\nR9: 8th pair | S081_iOme | S247_iOme | 6 per pair\nR10: 9th pair | S123_iOme | S113_iOme | 6 per pair\nR11: 10th pair | S139_pPer | S084_pAdn | 6 per pair\nR12: 11th pair | S015_iOme | S027_iOme | 6 per pair\nR13: 12th pair | S084_iOme | S139_iOme | 6 per pair\nR14: 13th pair | S027_pOme | S015_pPer | 6 per pair\nR15: 14th pair | S032_pOme | S229_pPer | 6 per pair\nR16: 15th pair | S229_iOme | S032_iOvaL | 6 per pair\nR20: | Block name | Slide name\nR21: | MH20-28407 1E | S015_iOme\nR22: | MH20-2308 2A | S015_pPer\nR23: | MH20-23951 1E | S027_pOme\nR24: | MH20-55984 2A | S027_iOme\nR25: | MH20-33501 1D | S032_pOme\nR26: | MH20-57200 5A | S032_iOvaL\nR27: | MH20-69162 1F | S084_pAdn\nR28: | MH21-23565 7E | S084_iOme\nR29: | MH22-26449 1A | S139_pPer\nR30: | MH22-51866 | S139_iOme\nR31: | MH23-8553 1A | S229_pPer\nR32: | MH23-8403 | S229_iOme\nR35: Note up is towards the + sign and down towards to label side.\nR36: 5 um thick sections in series\n\n1866 | S139_iOme\nR31: | MH23-8553 1A | S229_pPer\nR32: | MH23-8403 | S229_iOme\nR35: Note up is towards the + sign and down towards to label side.\nR36: 5 um thick sections in series\nR37: pairs will have 6 slides each | EG : Same slide\nR38: | 9_S309_ iOme_1_1_up | 9_S225_iOme_1_1_down\nR39: | 9_S309_ iOme_2_1_up | 9_S225_iOme_2_1_down\nR40: | 9_S309_ iOme_3_1_up | 9_S225_iOme_3_1_down\nR41: | 9_S309_ iOme_4_1_up | 9_S225_iOme_4_1_down\nR42: | 9_S309_ iOme_5_1_up | 9_S225_iOme_5_1_down\nR43: | 9_S309_ iOme_6_1_up | 9_S225_iOme_6_1_down","metadata":{"source":{"filename":"2024_12_19_EyeMT_9_with_TLS_7_GeoMxslides_Sectioning_Order .xlsx","stem":"2024_12_19_EyeMT_9_with_TLS_7_GeoMxslides_Sectioning_Order ","extension":".xlsx","relative_path":"Orders for slides and sections/2024_Sectioning orders/2024_12_19_EyeMT_9_with_TLS_7_GeoMxslides_Sectioning_Order .xlsx","absolute_path":"/Users/debashishdeb/Downloads/OMEIA-database/WET_LAB/Orders for slides and sections/2024_Sectioning orders/2024_12_19_EyeMT_9_with_TLS_7_GeoMxslides_Sectioning_Order .xlsx","size_bytes":19675,"size_human":"19.21 KB","modified":"2025-10-01T00:56:54","mime_type":"application/vnd.openxmlformats-officedocument.spreadsheetml.sheet","hashes":{"md5":"f934c306d6b7bc8e4af72ad58af38460"}},"classification":{"family":"spreadsheet","extension":".xlsx","mime_type":"application/vnd.openxmlformats-officedocument.spreadsheetml.sheet","extractor":"openpyxl","status":"ok"},"extraction_metadata":{"sheet_names":["Sheet1 and NOTES","Sheet2"],"sheet_count":2},"converted_at":"2026-06-05T15:27:43"}}