{"document_id":"2f2c95c3adca3e67e1efddade24085c1","filename":"MAN-10155-04_GeoMx_DSP_Hibernating_Procedure_for_Extended_Shutdown_BSB.pdf","relative_path":"NanoString GeoMx/Protocols/Protocol 07.2024/MAN-10155-04_GeoMx_DSP_Hibernating_Procedure_for_Extended_Shutdown_BSB.pdf","section":"04_Wet_Lab","has_text":true,"chunk_count":6,"full_text":"FOR RESEARCH USE ONLY. Not for use in diagnostic procedures. August 2023 \n© 2022- 2024 Bruker Spatial Biology , Inc. All rights reserved. Bruker, Bruker Spatial Biology , the NanoString logo, GeoMx, CosMx, AtoMx, and nCounter are \ntrademarks or registered trademarks of Bruker Spatial Biology , Inc., in the United States and/or other countries. All other trademarks and/or service marks \nnot owned by Bruker Spati al Biology , Inc. that appear in this document are the property of their respective owners. \nGeoMx ® DSP Hibernating Procedure for Extended Shutdown \n \nMAN -10155 -04 \n \nIf the GeoMx DSP instrument will be inactive for 2 weeks or more, NanoString recommends following this \nhibernation protocol to flush the fluidic lines of instrument buffers and fill the lines with DEPC -treated (or other \nnuclease -free) water. When desired, the system can be returned to operational as described below. \n \n(Please note that t his procedure was revised in August 2023, and therefore differs from the procedure printed in \nthe GeoMx DSP Instrument User Manual for v3.0 (July 2023). The procedure in the u ser manual will be updated \nwhen the manual is next revised.) \n \nMaterials \n• Two 1 L bottles of DEPC -treated or other nuclease -free water. Note: Thermo Fisher ® AM9922 Ambion ® DEPC -\nTreated Water (1 L) has the correct threading to match the Buffer S bottle tops.\n\nottles of DEPC -treated or other nuclease -free water. Note: Thermo Fisher ® AM9922 Ambion ® DEPC -\nTreated Water (1 L) has the correct threading to match the Buffer S bottle tops. An alternative to commercial \nDEPC -treated water is DEPC -treated water prepared in -house, following standard lab protocols. \n• 1 spare tissue slide (for example, the tissue slide used in GeoMx training). A blank slide with a small indelible \npen mark in the center and in the label area may suffice. \n• 1 spare collection plate . \n \nHibernate the system \n1. Switch Buffer S bottles to DEPC -treated water bottles. Perform these steps without launching the Change \nReagents wizard : \na. Open the bottle bay door and unscrew the bottle cap assemblies from the Buffer S bottles in bottle slots \n1 and 4. \nb. Replace these two bottles with DEPC -treated water. Close the b ottle bay door. \nc. Cap and save your bottles of Buffer S to use when returning the system to operational. \n2. Prime lines: \na. From the Administration menu, select Admin Scripts (you must be logged in as an administrative user) . \nFrom the dropdown menu, select Admin_SystemPrimeFromBottle . In the field for Parameter Value, \nenter 1. Click Proceed . The instrument prime s the Bottle 1 line (allow 8 minutes to complete). \nb. Leave the Admin Scripts page, then select Admin Scripts again. Enter Parameter Value of 4. Click \nProceed .\n\ninstrument prime s the Bottle 1 line (allow 8 minutes to complete). \nb. Leave the Admin Scripts page, then select Admin Scripts again. Enter Parameter Value of 4. Click \nProceed . The instrument prime s the Bottle 4 line ( allow 8 minutes to complete). \n3. Begin a mock run to push water through fluidic lines: \na. Start a new run by clicking New Data Collection , or Data Collection then New/Continue Run. If these \nbuttons are not available, click Assist (wrench icon)  Restart Data Collection Workflow . When \nprompted: \n1. Insert slide holder with a spare slide in s lot 1, covered with DEPC -treated water. \n2. Insert the spare collection plate. \n3. Select any Morphology Marker kit from the dropdown menu. Do not select any Probe Kit. The \nsystem will warn that you will not be able to collect from this slide. \n4. Proceed to the low magnification scan. \nb. Define a scan area in the low magnification scan to proceed to the high magnification scan. \nc. When the high magnification scan is complete, the system will initiate cleaning and move to the \nCollection Complete idle software state. \nd. Once at the Collection Complete idle software state, click on Remove Slides and Microplate .\n\nGeoMx DSP Hibernating Procedure for Extended Shutdown MAN -10155 -04 \n \nFOR RESEARCH USE ONLY. Not for use in diagnostic procedures . \n2 \n \ne. When prompted, o pen the door to retrieve the slide holder. Store the slide, thoroughly clean the slide \nholder, and return the holder to inside the instrument. \nf. Remove the collection plate and keep as a spare. \ng. When finished, close the door to the instrument. \n4. Turn off the instrument (optional) : \na. Select the Administration tab from the GeoMx DSP Control Center. \nb. Select System Settings  System Shutdown  Shutdown System . \nc. When the screen turns black ( after ~30 sec onds), power off by flipping the switch on the back- right of \nthe instrument. \n \nReturn the system to operational \n1. Switch DEPC -treated water bottles to Buffer S bottles. Perform these steps without launching the Change \nReagents wizard : \na. Open the bottle bay door and unscrew the bottle cap assemblies from the DEPC -treated water bottles \nin bottle slots 1 and 4. \nb. Replace these two bottles with the Buffer S bottles that were removed previously. Close the b ottle bay \ndoor. \n2. Power On the instrument , if it was off: \na. Flip the switch on the back- right of the instrument to On. The system will boot up, which may take a few \nminutes. \nb. Log in to the Control Center using an administrative user account . \n3. Prime lines: \na.\n\nright of the instrument to On. The system will boot up, which may take a few \nminutes. \nb. Log in to the Control Center using an administrative user account . \n3. Prime lines: \na. From the Administration menu, select Admin Scripts . From the dropdown menu, select \nAdmin_SystemPrimeFromBottle . In the field for Parameter Value, enter 1. Click Proceed . The instrument \nprime s the Bottle 1 line ( allow 8 minutes to complete ). \nb. Leave the Admin Scripts page, then select Admin Scripts again. Enter Parameter Value of 4. Click \nProceed . The instrument prime s the Bottle 4 line ( allow 8 minutes to complete). \n4. Begin a mock run to push buffer through fluidic lines: \na. Start a new run by clicking New Data Collection ; or Data Collection then New/Continue Run . If these \nbuttons are not available, click Assist (wrench icon)  Restart Data Collection Workflow . When \nprompted: \n1. Insert slide holder with a spare slide in s lot 1, covered with Buffer S. \n2. Insert the spare collection plate. \n3. Select any Morphology Marker kit from the dropdown menu. Do not select any Probe Kit. The \nsystem will warn that you will not be able to collect from this slide. \n4. Proceed through the Preparing Instrument and Initializing Fluidics steps to generate a low \nmagnification scan. \nb. Define a scan area in the low magnification scan to proceed to the high magnification scan. \nc.\n\nnstrument and Initializing Fluidics steps to generate a low \nmagnification scan. \nb. Define a scan area in the low magnification scan to proceed to the high magnification scan. \nc. When the high magnification scan is complete, the system will initiate cleaning and move to the \nCollection Complete idle software state. \nd. Once at the Collection Complete idle software state, click on Remove Slides and Microplate . \ne. When prompted, o pen the door to retrieve the slide holder. Store the slide, thoroughly clean the slide \nholder , and return the holder to inside the instrument. \nf. You may remove the spare collection plate (and save for similar uses). \ng. When finished, close the door to the instrument. \n \nIf the instrument was kept on during the hibernation, it is recommended to restart it before the next run. \nContact Support@nanostring.com for technical support.","metadata":{"source":{"filename":"MAN-10155-04_GeoMx_DSP_Hibernating_Procedure_for_Extended_Shutdown_BSB.pdf","stem":"MAN-10155-04_GeoMx_DSP_Hibernating_Procedure_for_Extended_Shutdown_BSB","extension":".pdf","relative_path":"NanoString GeoMx/Protocols/Protocol 07.2024/MAN-10155-04_GeoMx_DSP_Hibernating_Procedure_for_Extended_Shutdown_BSB.pdf","absolute_path":"/Users/debashishdeb/Downloads/OMEIA-database/WET_LAB/NanoString GeoMx/Protocols/Protocol 07.2024/MAN-10155-04_GeoMx_DSP_Hibernating_Procedure_for_Extended_Shutdown_BSB.pdf","size_bytes":489820,"size_human":"478.34 KB","modified":"2026-05-26T00:44:42","mime_type":"application/pdf","hashes":{"md5":"f409857d70831824e6702cd1ea0b34d1"}},"classification":{"family":"pdf","extension":".pdf","mime_type":"application/pdf","extractor":"PyMuPDF/pypdf/PyPDF2","status":"ok"},"extraction_metadata":{"page_count":2},"converted_at":"2026-06-05T15:27:42"}}