{"document_id":"387b16b774466614295cdec3fe7c12a6","filename":"CyCIF manual protocol_Färkkilä lab.docx","relative_path":"Protocols, instructions/Archive 2.0/CyCIF manual protocol_Färkkilä lab.docx","section":"04_Wet_Lab","has_text":true,"chunk_count":96,"full_text":"t-CyCIF protocol\n\nDay 0\n\nPreparations\n\nMake sure that the tissue section being stained is not older than 6 months and has been stored at +40C.\n\nSet the oven’s temperature to 560C (double check the temperature using a thermometer).\n\nCheck the levels of xylene and alcohol in the dewaxing and rehydration series in the fume hood, if the levels are too low add more xylene or respective alcohol. Prepare fresh xylene and alcohol series after using them 5 times.\n\nMake sure that all the buffers and antibodies are available: antigen retrieval (100mM citric acid pH 6.0), odyssey blocking buffer, 30% H202, & 480mM NaOH, and 1x PBS.\n\nDay 1 (approx. 6.5 h)\n\nDewaxing and antigen retrieval (approx. 2h 10 min)\n\nBaking: place the slides vertically into a grey plastic slide holder and bake in a 560C oven for 30 min.\n\nDeparaffinization + rehydration:\n\n3 x 5 min Xylene\n\n1 x 3 min 100% ethanol\n\n1 x 3 min 90% ethanol\n\n1 x 3 min 70% ethanol\n\n1 x 3 min 50% ethanol\n\n1 x 3 min 30% ethanol\n\n2 x 1 min successive 1x PBS solution\n\nAntigen retrieval:\n\nAlways use freshly prepared citric acid buffer, 10 mM, pH 6.0:\n\nFrom 100mM stock 🡪 25mL of stock solution + 225mL of MQ.\n\n100 mM citric acid 1L:\n\nDissolve 21.0 grams of citric acid monohydrate (Sigma #C1909) to 800 mL of MQ H20.\n\nAdd 9.94 grams of NaOH pellets (Merck # 1310-73-2)\n\nLeave on a magnetic stirrer to thoroughly mix\n\nMeasure the pH and set to 6.0\n\nLevel the volume up to 1L with MQ H20.\n\nNote: Use the solution not more than 6 months after preparation\n\nTransfer the slides onto a white plastic holder and in a glass dish - fill with 250 mL citric acid buffer.\n\nBoil sections in a microwave at 600 W as follows:\n\nBoil for 4 min - leave the slides inside for 5 min.\n\nBoil for 2 min - leave the slides inside for 5 min.\n\nBoil for 2 min.\n\nLet to cool down for 20 mins RT\n\nWash three times with 1x PBS, ~ 3 min each.\n\n2. Pre-staining (approx. 2h)\n\nPrepare a moist incubation chamber to minimize evaporation: Wet regular tissue paper under the tap water and fold it to fit inside the grey slide box. After cooling and washing from step 1.3., take out the slides one at a time, dry the surroundings of the tissue section using soft fiber-free tissue paper. Without letting the tissue dry, quickly add 200-300 uL odyssey blocking buffer per section and incubate for 30 min RT. The use of PAP pen is not needed. Do not spread the blocking buffer with a pipette tip, as you might scratch the tissue while doing so. In addition, thorough drying of the surroundings of the tissue creates a hydrophobic surface so that the solution does not spread outside the tissue.\n\nAfter the incubation, remove the blocking buffer by vertically tapping the slide on a tissue paper. Next, pre-stain the slides with secondary antibodies and Hoechst only by adding 200-300uL of pre-diluted antibodies per section. Incubate for 60 min at RT in a moist chamber (from 2.1.).\n\nPrepare cocktail of secondary antibodies and Hoechst in odyssey blocking buffer:\n\n488 goat anti-rabbit 1:1000\n\n555 donkey anti-goat 1:1000\n\n647 goat anti-mouse 1:1000\n\nHOECHST 1:5000\n\nTransfer the slides into a vertical grey plastic holder placed in a white plastic container with 1xPBS. Wash three times with 1x PBS, ~ 3 min each.\n\n3. Bleaching/Fluorophore inactivation (approx. 2h)\n\nPrepare 50 mL bleaching solution in a falcon tube as follows:\n\n40 ml 1xPBS\n\n7.5ml 30% H2O2\n\n2.5ml 480 mM NaOH\n\nPour the bleaching solution into a white slide box lid placed on top of a LED light.\n\nUsing forceps, transfer the slides into a bleaching solution; make sure that the slides are completely immersed in the solution. Place another LED light on top of the slide box (step 3.2). Connect bottom and top LED lights to power.\n\nPhotobleach the sides for 90 min at RT, during which change the buffer solution after every 30 min.\n\nWash four times in PBS, ~ 3 min each.\n\nNOTE: Only for cycles 0 and 1 change the bleaching solution 2x after every 30 min. The rest of the cycles are only 1x after 45 min.\n\n4. Staining with secondaries and Hoechst (approx. 15 min)\n\n4.1. During the washing step from 3.4., prepare a cocktail of secondary antibodies and Hoechst in\n\nodyssey blocking buffer:\n\n488 goat anti-rabbit 1:2000\n\n555 donkey anti-goat 1:2000\n\n647 goat anti-mouse 1:2000\n\nHOECHST 1:10 000\n\nNOTE: dilutions are different from step 2.2.\n\n4.2. Add 200-300uL per section and incubate at +4°C o/n in a moist chamber (from 2.1.)\n\nDay 2\n\nWash the slides three times in 1x PBS, ~ 3 min each\n\nDry the surroundings of the tissue section using soft fiber-free tissue paper. Add 100 uL of 70%\n\nglycerol per section and carefully cover with a coverslip, avoiding air bubbles.\n\nScan the slides.\n\nNOTE: Remove excess glycerol from the surrounding of the slides; the slide holder will become dirty if the slide edges are moist and contain excess glycerol.\n\nDe-coverslipping\n\n5.1. Prewarm 1x PBS to about +40°C.\n\n5.2. Using the grey slide holder, immerse the slides vertically into the prewarmed 1x PBS. Leave for\n\nabout 5 min. Carefully lift the slides and place them into another grey slide holder in a white plastic\n\ncontainer with 1x PBS. NOTE: when lifting the slide, the coverslip should automatically come off.\n\nLeave the slides in the prewarmed 1x PBS for another 5 min if this does not happen. Repeat with\n\na new batch of warm PBS if needed.\n\n5.3. Wash three times with RT 1x PBS, ~ 3 min each.\n\nStaining with primary antibodies\n\n6.1. Stain with unconjugated primary antibodies o/n at +4°C diluted in Odyssey solution.\n\nDay 3\n\nStaining with secondary antibodies\n\n7.1. Wash three times with 1x PBS, ~ 3 min each.\n\nIncubate secondary antibodies 1:2000 and Hoechst 1:10000 in Odyssey buffer for 1 hr RT\n\n7.2. Wash three times with 1x PBS x3, ~ 3 min each.\n\n7.3. Dry the surroundings of the tissue section using soft fiber-free tissue paper. Add 100 uL of 70%\n\nglycerol per section and carefully cover with a coverslip, avoiding air bubbles.\n\n7.4. Scan the slides.\n\nNote: Volume of the 70% glycerol depends on the size of the tissue, bigger tissues may need more than 100ul for example 1cm x 1cm tissue might need 120 ul of glycerol\n\n8. Cyclic phase – repeat steps as before\n\n8.1. Decoverslip using a prewarmed 1x PBS\n\n8.2. Photobleach for 1.5 h, change the solution after 45 min.\n\n8.3. Wash four times in PBS, ~ 3 min each.\n\n8.4. Stain with pre-conjugated antibodies and Hoechst 1:10000 o/n at +4°C.\n\n8.5. Wash three times with 1x PBS, ~ 3 min each.\n\n8.6. Mount with 70% glycerol and scan\n\nRepeat step 8 for the next round","metadata":{"source":{"filename":"CyCIF manual protocol_Färkkilä lab.docx","stem":"CyCIF manual protocol_Färkkilä lab","extension":".docx","relative_path":"Protocols, instructions/Archive 2.0/CyCIF manual protocol_Färkkilä lab.docx","absolute_path":"/Users/debashishdeb/Downloads/OMEIA-database/WET_LAB/Protocols, instructions/Archive 2.0/CyCIF manual protocol_Färkkilä lab.docx","size_bytes":205500,"size_human":"200.68 KB","modified":"2024-09-16T02:41:12","mime_type":"application/vnd.openxmlformats-officedocument.wordprocessingml.document","hashes":{"md5":"b165c6e030312a80c9d4c48cead1b840"}},"classification":{"family":"word","extension":".docx","mime_type":"application/vnd.openxmlformats-officedocument.wordprocessingml.document","extractor":"python-docx","status":"ok"},"extraction_metadata":{"paragraph_count":96,"table_count":0,"core_properties":{"title":"","subject":"","author":"Nagaraj, Ashwini S","keywords":"","created":"2020-01-28T11:45:00+00:00","modified":null,"last_modified_by":""}},"converted_at":"2026-06-05T15:27:47"}}