{"document_id":"921136eeb2738e262eaf6324aec0e591","filename":"COI Form - _AF.pdf","relative_path":"38_ADC_project/6_Archive/2_ESGO_2026/COI Form - _AF.pdf","section":"24_38_adc_project-20260602t172138z-3-001","has_text":true,"chunk_count":2,"full_text":"E U R O PE AN U N ION O F ME D I CAL SP E C IAL I S T S ( UEM S )\nE U R O P E A N A C C R E D I T A T I O N C O U N C I L F O R C M E ( E A C C M E ® ) \nRUE DE L’INDUSTRIE 24, BE- 1040 BRUSSELS \n T + 32 2 649 51 64 \neaccme.uems.eu - accreditation@uems.eu \nUEMS aisbl – Union Européenne des Médecins Spécialistes \n VAT n° BE 0469.067.848 RPM Bruxelles -Brussels \nEU Transparency Register ID 2190387 30914 -92 \nConflict of Interest Disclosure Form \n(to be completed by Scientific/ Organizing Committee Members) \nNAME: ………Anniina Färkkilä…………………………………. \nAFFILIATION: ………University of Helsini and Helsinki University Hospital………………………………. \nIn accordance with criterion 1 3 of document UEMS 20 23/07 “EACCME® Criteria for the Accreditation of \nLive Educational Events (LEEs)”, all declarations of perceived or actual conflicts of interest for the last 3 \nyears , whether due to a financial or other relationship, must be provided to the EACCME® upon \nsubmission of the application. COI declarations signe d more than 6 months before the date of the event \nwill not be accepted. Declarations must be made available online on the event website of the LEE. \nDeclarations must include whether any fee, honorarium or arrangement for re -imbursement of expenses \nin relat ion to the LEE has been provided. \nDISCLOSURE \n❑I have no potential conflict of interest to report\n\nher any fee, honorarium or arrangement for re -imbursement of expenses \nin relat ion to the LEE has been provided. \nDISCLOSURE \n❑I have no potential conflict of interest to report\n❑I have the following potential conflict(s) of interest to report\nName of commercial company Type of affiliation / financ ial interest \nReceipt of grants/research supports: \nReceipt of honoraria or consultation fees: \nParticipation in a company sponsored speaker’s \nbureau: \nStock shareholder: \nSpouse/partner: \nOther support (please specify): \nSignature: Date: \nAbbvie\nAbbvie, GSK, Astra Zeneca\n18.10.2025","metadata":{"source":{"filename":"COI Form - _AF.pdf","stem":"COI Form - _AF","extension":".pdf","relative_path":"38_ADC_project/6_Archive/2_ESGO_2026/COI Form - _AF.pdf","absolute_path":"/Users/debashishdeb/Downloads/OMEIA-database/projects/38_ADC_project-20260602T172138Z-3-001/38_ADC_project/6_Archive/2_ESGO_2026/COI Form - _AF.pdf","size_bytes":405387,"size_human":"395.89 KB","modified":"2026-05-27T02:23:52","mime_type":"application/pdf","hashes":{"md5":"b29a8e1d19002e3dbe288b5ca011c842"}},"classification":{"family":"pdf","extension":".pdf","mime_type":"application/pdf","extractor":"PyMuPDF/pypdf/PyPDF2","status":"ok"},"extraction_metadata":{"page_count":1},"converted_at":"2026-06-05T15:28:36"}}